transmeet/__init__.py
transmeet/cli.py
transmeet/processor.py
transmeet/clients/__init__.py
transmeet/clients/audio_client.py
transmeet/clients/llm_client.py
transmeet/clients/transcription_client.py
transmeet/utils/__init__.py
transmeet/utils/audio_utils.py
transmeet/utils/file_utils.py
transmeet/utils/general_utils.py
transmeet/utils/json_parser.py
transmeet-0.0.26.dist-info/METADATA
transmeet-0.0.26.dist-info/WHEEL
transmeet-0.0.26.dist-info/entry_points.txt
transmeet-0.0.26.dist-info/top_level.txt
transmeet-0.0.26.dist-info/RECORD
