Metadata-Version: 2.4
Name: transmeet
Version: 0.0.26
Summary: LLM-powered meeting transcription and summarization tool.
Home-page: https://github.com/codeperfectplus/transmeet
Author: Deepak Raj
Author-email: deepak008@live.com
License: MIT
Project-URL: Source, https://github.com/codeperfectplus/transmeet
Project-URL: Issues, https://github.com/codeperfectplus/transmeet/issues
Project-URL: Documentation, https://transmeet.readthedocs.io/en/latest/
Keywords: transcription,meeting summarization,audio processing,LLM,Groq,Google Speech,CLI,automation,speak2summary
Classifier: Development Status :: 3 - Alpha
Classifier: Programming Language :: Python :: 3
Classifier: Programming Language :: Python :: 3.8
Classifier: Programming Language :: Python :: 3.9
Classifier: Programming Language :: Python :: 3.10
Classifier: License :: OSI Approved :: MIT License
Classifier: Operating System :: OS Independent
Classifier: Intended Audience :: Developers
Classifier: Topic :: Software Development :: Libraries
Classifier: Topic :: Multimedia :: Sound/Audio :: Analysis
Requires-Python: >=3.8
Requires-Dist: pydub==0.25.1
Requires-Dist: groq==0.24.0
Requires-Dist: SpeechRecognition==3.14.2
Requires-Dist: openai==1.78.0
Dynamic: author
Dynamic: author-email
Dynamic: classifier
Dynamic: description
Dynamic: description-content-type
Dynamic: home-page
Dynamic: keywords
Dynamic: license
Dynamic: project-url
Dynamic: requires-dist
Dynamic: requires-python
Dynamic: summary
